instrumentum/__init__.py
instrumentum/analysis/__init__.py
instrumentum/analysis/dashboards.py
instrumentum/analysis/dataframes.py
instrumentum/analysis/distribution_analyzer.py
instrumentum/analysis/plots.py
instrumentum/feature_generation/__init__.py
instrumentum/feature_generation/interactions.py
instrumentum/feature_preprocess/__init__.py
instrumentum/feature_preprocess/utils.py
instrumentum/feature_selection/__init__.py
instrumentum/feature_selection/correlation.py
instrumentum/feature_selection/stepwise.py
instrumentum/image_processing/__init__.py
instrumentum/model_tuning/__init__.py
instrumentum/model_tuning/_optuna_dispatchers.py
instrumentum/model_tuning/wrapper_optuna.py
instrumentum/time_series/__init__.py
instrumentum/utils/__init__.py
instrumentum/utils/_decorators.py
instrumentum/utils/utils.py
instrumentum-0.10.1.dist-info/LICENSE
instrumentum-0.10.1.dist-info/WHEEL
instrumentum-0.10.1.dist-info/METADATA
instrumentum-0.10.1.dist-info/RECORD
