Metadata-Version: 2.1
Name: instrumentum
Version: 0.10.1
Summary: General utilities for data science projects
License: MIT
Author: Federico Montanana
Requires-Python: >=3.8,<3.11
Classifier: License :: OSI Approved :: MIT License
Classifier: Programming Language :: Python :: 3
Classifier: Programming Language :: Python :: 3.10
Classifier: Programming Language :: Python :: 3.8
Classifier: Programming Language :: Python :: 3.9
Requires-Dist: joblib (>=1.1.0,<2.0.0)
Requires-Dist: numpy (==1.22.4)
Requires-Dist: optbinning (>=0.13.0,<0.14.0)
Requires-Dist: optuna (>=2.10.0,<3.0.0)
Requires-Dist: pandas (>=1.3.3,<2.0.0)
Requires-Dist: seaborn (>=0.11.2,<0.12.0)
Requires-Dist: sklearn (>=0.0,<0.1)
